LICENSE
MANIFEST.in
README.rst
plugin.json
requirements.txt
setup.py
romanesco/__init__.py
romanesco/__main__.py
romanesco/events.py
romanesco/utils.py
romanesco/worker.dist.cfg
romanesco.egg-info/PKG-INFO
romanesco.egg-info/SOURCES.txt
romanesco.egg-info/dependency_links.txt
romanesco.egg-info/entry_points.txt
romanesco.egg-info/not-zip-safe
romanesco.egg-info/requires.txt
romanesco.egg-info/top_level.txt
romanesco/executors/__init__.py
romanesco/executors/python.py
romanesco/executors/workflow.py
romanesco/format/__init__.py
romanesco/format/boolean/boolean_to_json.json
romanesco/format/boolean/boolean_to_json.py
romanesco/format/boolean/json_to_boolean.json
romanesco/format/boolean/json_to_boolean.py
romanesco/format/boolean/validate_boolean.json
romanesco/format/boolean/validate_json.json
romanesco/format/directory/path_to_tgz.json
romanesco/format/directory/path_to_tgz.py
romanesco/format/directory/path_to_zip.json
romanesco/format/directory/path_to_zip.py
romanesco/format/directory/tgz_to_path.json
romanesco/format/directory/tgz_to_path.py
romanesco/format/directory/validate_path.json
romanesco/format/directory/validate_tgz.json
romanesco/format/directory/validate_zip.json
romanesco/format/directory/zip_to_path.json
romanesco/format/directory/zip_to_path.py
romanesco/format/graph/adjacencylist_to_networkx.json
romanesco/format/graph/adjacencylist_to_networkx.py
romanesco/format/graph/clique_json_to_networkx.json
romanesco/format/graph/clique_json_to_networkx.py
romanesco/format/graph/graphml_to_networkx.json
romanesco/format/graph/graphml_to_networkx.py
romanesco/format/graph/networkx_json_to_networkx.json
romanesco/format/graph/networkx_json_to_networkx.py
romanesco/format/graph/networkx_to_adjacencylist.json
romanesco/format/graph/networkx_to_adjacencylist.py
romanesco/format/graph/networkx_to_clique_json.json
romanesco/format/graph/networkx_to_clique_json.py
romanesco/format/graph/networkx_to_graphml.json
romanesco/format/graph/networkx_to_graphml.py
romanesco/format/graph/networkx_to_networkx_json.json
romanesco/format/graph/networkx_to_networkx_json.py
romanesco/format/graph/validate_clique_json.json
romanesco/format/graph/validate_graph_adjacencylist.json
