Metadata-Version: 1.1
Name: romanesco
Version: 0.2.0
Summary: Batch execution engine built on celery.
Home-page: http://romanesco.readthedocs.org
Author: Kitware, Inc.
Author-email: kitware@kitware.com
License: Apache 2.0
Platform: UNKNOWN
Classifier: Development Status :: 4 - Beta
Classifier: Environment :: Console
Classifier: License :: OSI Approved :: Apache Software License
Classifier: Operating System :: OS Independent
Classifier: Programming Language :: Python :: 2
